kibana_api
