Metadata-Version: 2.1
Name: kibana-api
Version: 0.0.4
Summary: This is an API mapping library for Kibana API to generate visualizations and dashboards automatically
Home-page: https://github.com/cr0wg4n/kibana-api
Author: Mauricio Matias Conde
Author-email: mcm.crw@gmail.com
License: MIT
Project-URL: Bug Tracker, https://github.com/cr0wg4n/kibana-api/issues
Keywords: elasticsearch,kibana,development,api mapping
Platform: UNKNOWN
Classifier: Programming Language :: Python :: 3
Classifier: License :: OSI Approved :: MIT License
Classifier: Operating System :: OS Independent
Classifier: Development Status :: 3 - Alpha
Classifier: Intended Audience :: Developers
Classifier: Topic :: Software Development :: Build Tools
Requires-Python: >=3.0
License-File: LICENSE
